dyna_fetch/__init__.py
dyna_fetch/client.py
dyna_fetch/filters.py
dyna_fetch/py.typed
dyna_fetch/services.py
dyna_fetch-0.1.0.dist-info/METADATA
dyna_fetch-0.1.0.dist-info/WHEEL
dyna_fetch-0.1.0.dist-info/entry_points.txt
dyna_fetch-0.1.0.dist-info/licenses/LICENSE
dyna_fetch-0.1.0.dist-info/RECORD
