Metadata-Version: 2.4
Name: dyna-fetch
Version: 0.1.0
Summary: Python library to fetch data from BusinessCentral odata API.
Author-email: akshpra <prabhuakshay9803@gmail.com>
License-File: LICENSE
Requires-Python: >=3.12
Requires-Dist: arrow>=1.3.0
Requires-Dist: httpx>=0.28.1
Requires-Dist: loguru>=0.7.3
Requires-Dist: msgspec>=0.19.0
